setup.cfg
setup.py
wcleaner/__init__.py
wcleaner/core.py
wcleaner/junkcenter.py
wcleaner/settings.py
wcleaner.egg-info/PKG-INFO
wcleaner.egg-info/SOURCES.txt
wcleaner.egg-info/dependency_links.txt
wcleaner.egg-info/entry_points.txt
wcleaner.egg-info/requires.txt
wcleaner.egg-info/top_level.txt