Metadata-Version: 1.1
Name: wcleaner
Version: 1.0.0
Summary: Disk Space Cleaner
Home-page: https://github.com/ruiqi/wcleaner
Author: ruiqi
Author-email: smile.ruiqi@gmail.com
License: License :: OSI Approved :: MIT License
Download-URL: https://github.com/ruiqi/wcleaner/archive/v1.0.0.tar.gz
Keywords: disk,cleaner,walk,scandir
Platform: UNKNOWN
